{
    "$schema": "https://moj-analytical-services.github.io/metadata_schema/table/v1.4.0.json",
    "name": "pay",
    "description": "Check glue specific works",
    "data_format": "csv",
    "location": "pay/",
    "columns": [
        {
            "name": "employee_id",
            "type": "int",
            "description": "an ID for each employee"
        },
        {
            "name": "annual_salary",
            "type": "float",
            "description": "Annual salary"
        }
    ],
    "glue_specific": {
        "Parameters": {
            "skip.header.line.count": "1"
        },
        "StorageDescriptor": {
            "Parameters": {
                "skip.header.line.count": "1"
            }
        }
    },
    "primary_key": [
        "employee_id"
    ]
}
